opensemantic/core/__init__.py
opensemantic/core/_model.py
opensemantic_core-0.44.3.dev1.dist-info/licenses/LICENSE.txt
opensemantic_core-0.44.3.dev1.dist-info/METADATA
opensemantic_core-0.44.3.dev1.dist-info/WHEEL
opensemantic_core-0.44.3.dev1.dist-info/top_level.txt
opensemantic_core-0.44.3.dev1.dist-info/RECORD
