Metadata-Version: 2.4
Name: opensemantic.core
Version: 0.44.3.dev1
Summary: Library with Python models derived from the page package world.opensemantic.core
Home-page: https://github.com/OpenSemanticWorld-Packages/opensemantic.core-python
Author: OpenSemanticWorld
Author-email: team@opensemantic.world
License: Apache 2.0
Project-URL: Documentation, https://github.com/OpenSemanticWorld-Packages/opensemantic.core-python
Project-URL: Source, https://github.com/OpenSemanticWorld-Packages/opensemantic.core-python
Project-URL: Tracker, https://github.com/OpenSemanticWorld-Packages/opensemantic.core-python/issues
Platform: any
Classifier: Development Status :: 4 - Beta
Classifier: Programming Language :: Python
Requires-Python: >=3.9
License-File: LICENSE.txt
Requires-Dist: opensemantic
Provides-Extra: testing
Requires-Dist: setuptools; extra == "testing"
Requires-Dist: pytest; extra == "testing"
Requires-Dist: pytest-cov; extra == "testing"
Dynamic: license-file
